chunked_field/__init__.py
chunked_field/admin.py
chunked_field/apps.py
chunked_field/fields.py
chunked_field/models.py
chunked_field/serializers.py
chunked_field/migrations/0001_initial.py
chunked_field/migrations/__init__.py
demo/__init__.py
demo/admin.py
demo/apps.py
demo/models.py
demo/serializers.py
demo/tests.py
demo/urls.py
demo/views.py
demo/migrations/0001_initial.py
demo/migrations/__init__.py
mysite/__init__.py
mysite/asgi.py
mysite/settings.py
mysite/urls.py
mysite/wsgi.py
django_chunked_field-0.0.6.dist-info/LICENSE
django_chunked_field-0.0.6.dist-info/METADATA
django_chunked_field-0.0.6.dist-info/WHEEL
django_chunked_field-0.0.6.dist-info/top_level.txt
django_chunked_field-0.0.6.dist-info/RECORD
