Metadata-Version: 2.1
Name: django-chunked-field
Version: 0.0.6
Summary: A Django app providing a ChunkedTextField for storing large text data in chunks.
Home-page: https://github.com/berkayeren/django-chunked-field
Author: berkayeren
Author-email: berkay-eren@hotmail.com
License: MIT License
Classifier: Environment :: Web Environment
Classifier: Framework :: Django
Classifier: Framework :: Django :: 3.2
Classifier: Intended Audience :: Developers
Classifier: License :: OSI Approved :: MIT License
Classifier: Programming Language :: Python
Classifier: Programming Language :: Python :: 3
License-File: LICENSE
Requires-Dist: Django >=3.2
Requires-Dist: djangorestframework >=3.14.0
